fintrack/__init__.py
fintrack/__main__.py
fintrack/py.typed
fintrack/cli/__init__.py
fintrack/cli/analyze.py
fintrack/cli/budget.py
fintrack/cli/import_cmd.py
fintrack/cli/init.py
fintrack/cli/list_cmd.py
fintrack/cli/main.py
fintrack/cli/report.py
fintrack/cli/status.py
fintrack/cli/utils.py
fintrack/cli/validate.py
fintrack/core/__init__.py
fintrack/core/constants.py
fintrack/core/exceptions.py
fintrack/core/models.py
fintrack/core/workspace.py
fintrack/engine/__init__.py
fintrack/engine/aggregator.py
fintrack/engine/calculator.py
fintrack/engine/periods.py
fintrack/io/__init__.py
fintrack/io/csv_reader.py
fintrack/io/yaml_reader.py
fintrack/io/yaml_writer.py
fintrack/reports/__init__.py
fintrack/reports/generator.py
fintrack/storage/__init__.py
fintrack/storage/base.py
fintrack/storage/factory.py
fintrack/storage/sqlite/__init__.py
fintrack/storage/sqlite/cache.py
fintrack/storage/sqlite/database.py
fintrack/storage/sqlite/import_log.py
fintrack/storage/sqlite/transactions.py
fintrack_cli-0.1.2.dist-info/METADATA
fintrack_cli-0.1.2.dist-info/WHEEL
fintrack_cli-0.1.2.dist-info/entry_points.txt
fintrack_cli-0.1.2.dist-info/licenses/LICENSE
fintrack_cli-0.1.2.dist-info/RECORD
