Metadata-Version: 2.4
Name: fintrack-cli
Version: 0.1.2
Summary: Personal Finance Tracker CLI - budget planning and expense analysis
Project-URL: Homepage, https://github.com/alexeiveselov92/fintrack
Project-URL: Repository, https://github.com/alexeiveselov92/fintrack
Project-URL: Issues, https://github.com/alexeiveselov92/fintrack/issues
Author-email: Alexei Veselov <alexeiveselov92@gmail.com>
Maintainer-email: Alexei Veselov <alexeiveselov92@gmail.com>
License: MIT
License-File: LICENSE
Keywords: budget,cli,expense-tracker,finance,money,personal-finance,tracking
Classifier: Development Status :: 4 - Beta
Classifier: Environment :: Console
Classifier: Intended Audience :: End Users/Desktop
Classifier: License :: OSI Approved :: MIT License
Classifier: Operating System :: OS Independent
Classifier: Programming Language :: Python :: 3
Classifier: Programming Language :: Python :: 3.11
Classifier: Programming Language :: Python :: 3.12
Classifier: Programming Language :: Python :: 3.13
Classifier: Topic :: Office/Business :: Financial :: Accounting
Classifier: Topic :: Utilities
Classifier: Typing :: Typed
Requires-Python: >=3.11
Requires-Dist: jinja2>=3.1.0
Requires-Dist: pydantic>=2.0.0
Requires-Dist: pyyaml>=6.0.0
Requires-Dist: rich>=13.0.0
Requires-Dist: typer>=0.12.0
Provides-Extra: dev
Requires-Dist: mypy>=1.10.0; extra == 'dev'
Requires-Dist: pytest-cov>=4.0.0; extra == 'dev'
Requires-Dist: pytest>=8.0.0; extra == 'dev'
Requires-Dist: ruff>=0.4.0; extra == 'dev'
Requires-Dist: types-pyyaml>=6.0.0; extra == 'dev'
